cautogui/__init__.py
cautogui/cautogui.py
cautogui/cautogui_core.cp38-win_amd64.pyd
cautogui-1.2.2.dist-info/LICENSE
cautogui-1.2.2.dist-info/METADATA
cautogui-1.2.2.dist-info/WHEEL
cautogui-1.2.2.dist-info/top_level.txt
cautogui-1.2.2.dist-info/RECORD
