Metadata-Version: 2.1
Name: cautogui
Version: 1.2.2
Summary: High-performance GUI automation with C++ core
Author: danckard
License: MIT
Project-URL: Source, https://github.com/danckard/cautogui
Project-URL: Tracker, https://github.com/danckard/cautogui/issues
Requires-Python: >=3.8
License-File: LICENSE
